index_calculator/__init__.py
index_calculator/_ci_netcdfattrs.py
index_calculator/_climate_indicator.py
index_calculator/_consts.py
index_calculator/_indices.py
index_calculator/_outputwriter.py
index_calculator/_postprocessing.py
index_calculator/_preprocessing.py
index_calculator/_processing.py
index_calculator/_tables.py
index_calculator/_utils.py
index_calculator/_variable_conversion.py
index_calculator/_version.py
index_calculator/cli.py
index_calculator/index_calculator.py
index_calculator/tables/cf_conversion.json
index_calculator/tables/convert_to_frequency.json
index_calculator/tables/input_vars.json
index_calculator/tables/metadata.json
index_calculator/tables/projects.json
index_calculator/tables/xcalc.json
index_calculator-0.13.0.dist-info/licenses/AUTHORS.rst
index_calculator-0.13.0.dist-info/licenses/LICENSE
index_calculator-0.13.0.dist-info/METADATA
index_calculator-0.13.0.dist-info/WHEEL
index_calculator-0.13.0.dist-info/entry_points.txt
index_calculator-0.13.0.dist-info/top_level.txt
index_calculator-0.13.0.dist-info/RECORD
