Metadata-Version: 2.4
Name: index_calculator
Version: 0.13.0
Summary: Python index-calculator is an xclim wrapper
License: MIT License
Project-URL: homepage, https://index-calculator.readthedocs.io
Project-URL: documentation, https://index-calculator.readthedocs.io
Project-URL: repository, https://github.com/ludwiglierhammer/index_calculator.git
Project-URL: changelog, https://index-calculator.readthedocs.io/en/latest/history.html
Keywords: index_calculator
Classifier: Development Status :: 2 - Pre-Alpha
Classifier: Intended Audience :: Developers
Classifier: License :: OSI Approved :: MIT License
Classifier: Natural Language :: English
Classifier: Programming Language :: Python :: 3
Classifier: Programming Language :: Python :: 3.11
Classifier: Programming Language :: Python :: 3.12
Classifier: Programming Language :: Python :: 3.13
Requires-Python: >=3.11
License-File: LICENSE
License-File: AUTHORS.rst
Requires-Dist: xarray
Requires-Dist: dask
Requires-Dist: xclim>=0.56.0
Requires-Dist: pyhomogenize>=0.5.1
Requires-Dist: pint>=0.1
Requires-Dist: pooch
Dynamic: license-file
